
[
{
"country": "Afghanistan",
"flag": "\uD83C\uDDE6\uD83C\uDDEB",
"continent": "Asia"
},
{
"country": "Albania",
"flag": "\uD83C\uDDE6\uD83C\uDDF1",
"continent": "Europe"
},
{
"country": "Algeria",
"flag": "\uD83C\uDDE9\uD83C\uDDFF",
"continent": "Africa"
},
{
"country": "Andorra",
"flag": "\uD83C\uDDE6\uD83C\uDDE9",
"continent": "Europe"
},
{
"country": "Angola",
"flag": "\uD83C\uDDE6\uD83C\uDDF4",
"continent": "Africa"
},
{
"country": "Antigua and Barbuda",
"flag": "\uD83C\uDDE6\uD83C\uDDEC",
"continent": "North America"
},
{
"country": "Argentina",
"flag": "\uD83C\uDDE6\uD83C\uDDF7",
"continent": "South America"
},
{
"country": "Armenia",
"flag": "\uD83C\uDDE6\uD83C\uDDF2",
"continent": "Asia"
},
{
"country": "Australia",
"flag": "\uD83C\uDDE6\uD83C\uDDFA",
"continent": "Oceania"
},
{
"country": "Austria",
"flag": "\uD83C\uDDE6\uD83C\uDDF9",
"continent": "Europe"
},
{
"country": "Azerbaijan",
"flag": "\uD83C\uDDE6\uD83C\uDDFF",
"continent": "Asia"
},
{
"country": "Bahamas",
"flag": "\uD83C\uDDE7\uD83C\uDDF8",
"continent": "North America"
},
{
"country": "Bahrain",
"flag": "\uD83C\uDDE7\uD83C\uDDED",
"continent": "Asia"
},
{
"country": "Bangladesh",
"flag": "\uD83C\uDDE7\uD83C\uDDE9",
"continent": "Asia"
},
{
"country": "Barbados",
"flag": "\uD83C\uDDE7\uD83C\uDDE7",
"continent": "North America"
},
{
"country": "Belarus",
"flag": "\uD83C\uDDE7\uD83C\uDDFE",
"continent": "Europe"
},
{
"country": "Belgium",
"flag": "\uD83C\uDDE7\uD83C\uDDEA",
"continent": "Europe"
},
{
"country": "Belize",
"flag": "\uD83C\uDDE7\uD83C\uDDFF",
"continent": "North America"
},
{
"country": "Benin",
"flag": "\uD83C\uDDE7\uD83C\uDDEF",
"continent": "Africa"
},
{
"country": "Bhutan",
"flag": "\uD83C\uDDE7\uD83C\uDDF9",
"continent": "Asia"
},
{
"country": "Bolivia",
"flag": "\uD83C\uDDE7\uD83C\uDDF4",
"continent": "South America"
},
{
"country": "Bosnia and Herzegovina",
"flag": "\uD83C\uDDE7\uD83C\uDDE6",
"continent": "Europe"
},
{
"country": "Botswana",
"flag": "\uD83C\uDDE7\uD83C\uDDFC",
"continent": "Africa"
},
{
"country": "Brazil",
"flag": "\uD83C\uDDE7\uD83C\uDDF7",
"continent": "South America"
},
{
"country": "Brunei",
"flag": "\uD83C\uDDE7\uD83C\uDDF3",
"continent": "Asia"
},
{
"country": "Bulgaria",
"flag": "\uD83C\uDDE7\uD83C\uDDEC",
"continent": "Europe"
},
{
"country": "Burkina Faso",
"flag": "\uD83C\uDDE7\uD83C\uDDEB",
"continent": "Africa"
},
{
"country": "Burundi",
"flag": "\uD83C\uDDE7\uD83C\uDDEE",
"continent": "Africa"
},
{
"country": "Cabo Verde",
"flag": "\uD83C\uDDE8\uD83C\uDDFB",
"continent": "Africa"
},
{
"country": "Cambodia",
"flag": "\uD83C\uDDF0\uD83C\uDDED",
"continent": "Asia"
},
{
"country": "Cameroon",
"flag": "\uD83C\uDDE8\uD83C\uDDF2",
"continent": "Africa"
},
{
"country": "Canada",
"flag": "\uD83C\uDDE8\uD83C\uDDE6",
"continent": "North America"
},
{
"country": "Central African Republic",
"flag": "\uD83C\uDDE8\uD83C\uDDEB",
"continent": "Africa"
},
{
"country": "Chad",
"flag": "\uD83C\uDDF9\uD83C\uDDE9",
"continent": "Africa"
},
{
"country": "Chile",
"flag": "\uD83C\uDDE8\uD83C\uDDF1",
"continent": "South America"
},
{
"country": "China",
"flag": "\uD83C\uDDE8\uD83C\uDDF3",
"continent": "Asia"
},
{
"country": "Colombia",
"flag": "\uD83C\uDDE8\uD83C\uDDF4",
"continent": "South America"
},
{
"country": "Comoros",
"flag": "\uD83C\uDDF0\uD83C\uDDF2",
"continent": "Africa"
},
{
"country": "Congo (Congo-Brazzaville)",
"flag": "\uD83C\uDDE8\uD83C\uDDEC",
"continent": "Africa"
},
{
"country": "Costa Rica",
"flag": "\uD83C\uDDE8\uD83C\uDDF7",
"continent": "North America"
},
{
"country": "Croatia",
"flag": "\uD83C\uDDED\uD83C\uDDF7",
"continent": "Europe"
},
{
"country": "Cuba",
"flag": "\uD83C\uDDE8\uD83C\uDDFA",
"continent": "North America"
},
{
"country": "Cyprus",
"flag": "\uD83C\uDDE8\uD83C\uDDFE",
"continent": "Asia"
},
{
"country": "Czechia (Czech Republic)",
"flag": "\uD83C\uDDE8\uD83C\uDDFF",
"continent": "Europe"
},
{
"country": "Denmark",
"flag": "\uD83C\uDDE9\uD83C\uDDF0",
"continent": "Europe"
},
{
"country": "Djibouti",
"flag": "\uD83C\uDDE9\uD83C\uDDEF",
"continent": "Africa"
},
{
"country": "Dominica",
"flag": "\uD83C\uDDE9\uD83C\uDDF2",
"continent": "North America"
},
{
"country": "Dominican Republic",
"flag": "\uD83C\uDDE9\uD83C\uDDF4",
"continent": "North America"
},
{
"country": "Ecuador",
"flag": "\uD83C\uDDEA\uD83C\uDDE8",
"continent": "South America"
},
{
"country": "Egypt",
"flag": "\uD83C\uDDEA\uD83C\uDDEC",
"continent": "Africa"
},
{
"country": "El Salvador",
"flag": "\uD83C\uDDF8\uD83C\uDDFB",
"continent": "North America"
},
{
"country": "England",
"flag": "\uD83C\uDDEC\uD83C\uDDE7",
"continent": "Europe"
},
{
"country": "Equatorial Guinea",
"flag": "\uD83C\uDDEC\uD83C\uDDF6",
"continent": "Africa"
},
{
"country": "Eritrea",
"flag": "\uD83C\uDDEA\uD83C\uDDF7",
"continent": "Africa"
},
{
"country": "Estonia",
"flag": "\uD83C\uDDEA\uD83C\uDDEA",
"continent": "Europe"
},
{
"country": "Eswatini",
"flag": "\uD83C\uDDF8\uD83C\uDDFF",
"continent": "Africa"
},
{
"country": "Ethiopia",
"flag": "\uD83C\uDDEA\uD83C\uDDF9",
"continent": "Africa"
},
{
"country": "Fiji",
"flag": "\uD83C\uDDEB\uD83C\uDDEF",
"continent": "Oceania"
},
{
"country": "Finland",
"flag": "\uD83C\uDDEB\uD83C\uDDEE",
"continent": "Europe"
},
{
"country": "France",
"flag": "\uD83C\uDDEB\uD83C\uDDF7",
"continent": "Europe"
},
{
"country": "Gabon",
"flag": "\uD83C\uDDEC\uD83C\uDDE6",
"continent": "Africa"
},
{
"country": "Gambia",
"flag": "\uD83C\uDDEC\uD83C\uDDF2",
"continent": "Africa"
},
{
"country": "Georgia",
"flag": "\uD83C\uDDEC\uD83C\uDDEA",
"continent": "Asia"
},
{
"country": "Germany",
"flag": "\uD83C\uDDE9\uD83C\uDDEA",
"continent": "Europe"
},
{
"country": "Ghana",
"flag": "\uD83C\uDDEC\uD83C\uDDED",
"continent": "Africa"
},
{
"country": "Greece",
"flag": "\uD83C\uDDEC\uD83C\uDDF7",
"continent": "Europe"
},
{
"country": "Grenada",
"flag": "\uD83C\uDDEC\uD83C\uDDE9",
"continent": "North America"
},
{
"country": "Guatemala",
"flag": "\uD83C\uDDEC\uD83C\uDDF9",
"continent": "North America"
},
{
"country": "Guinea",
"flag": "\uD83C\uDDEC\uD83C\uDDF3",
"continent": "Africa"
},
{
"country": "Guinea-Bissau",
"flag": "\uD83C\uDDEC\uD83C\uDDFC",
"continent": "Africa"
},
{
"country": "Guyana",
"flag": "\uD83C\uDDEC\uD83C\uDDFE",
"continent": "South America"
},
{
"country": "Haiti",
"flag": "\uD83C\uDDED\uD83C\uDDF9",
"continent": "North America"
},
{
"country": "Honduras",
"flag": "\uD83C\uDDED\uD83C\uDDF3",
"continent": "North America"
},
{
"country": "Hungary",
"flag": "\uD83C\uDDED\uD83C\uDDFA",
"continent": "Europe"
},
{
"country": "Iceland",
"flag": "\uD83C\uDDEE\uD83C\uDDF8",
"continent": "Europe"
},
{
"country": "India",
"flag": "\uD83C\uDDEE\uD83C\uDDF3",
"continent": "Asia"
},
{
"country": "Indonesia",
"flag": "\uD83C\uDDEE\uD83C\uDDE9",
"continent": "Asia"
},
{
"country": "Iran",
"flag": "\uD83C\uDDEE\uD83C\uDDF7",
"continent": "Asia"
},
{
"country": "Iraq",
"flag": "\uD83C\uDDEE\uD83C\uDDF6",
"continent": "Asia"
},
{
"country": "Ireland",
"flag": "\uD83C\uDDEE\uD83C\uDDEA",
"continent": "Europe"
},
{
"country": "Israel",
"flag": "\uD83C\uDDEE\uD83C\uDDF1",
"continent": "Asia"
},
{
"country": "Italy",
"flag": "\uD83C\uDDEE\uD83C\uDDF9",
"continent": "Europe"
},
{
"country": "Jamaica",
"flag": "\uD83C\uDDEF\uD83C\uDDF2",
"continent": "North America"
},
{
"country": "Japan",
"flag": "\uD83C\uDDEF\uD83C\uDDF5",
"continent": "Asia"
},
{
"country": "Jordan",
"flag": "\uD83C\uDDEF\uD83C\uDDF4",
"continent": "Asia"
},
{
"country": "Kazakhstan",
"flag": "\uD83C\uDDF0\uD83C\uDDFF",
"continent": "Asia"
},
{
"country": "Kenya",
"flag": "\uD83C\uDDF0\uD83C\uDDEA",
"continent": "Africa"
},
{
"country": "Kiribati",
"flag": "\uD83C\uDDF0\uD83C\uDDEE",
"continent": "Oceania"
},
{
"country": "North Korea",
"flag": "\uD83C\uDDF0\uD83C\uDDF5",
"continent": "Asia"
},
{
"country": "South Korea",
"flag": "\uD83C\uDDF0\uD83C\uDDF7",
"continent": "Asia"
},
{
"country": "Kuwait",
"flag": "\uD83C\uDDF0\uD83C\uDDFC",
"continent": "Asia"
},
{
"country": "Kyrgyzstan",
"flag": "\uD83C\uDDF0\uD83C\uDDEC",
"continent": "Asia"
},
{
"country": "Laos",
"flag": "\uD83C\uDDF1\uD83C\uDDE6",
"continent": "Asia"
},
{
"country": "Latvia",
"flag": "\uD83C\uDDF1\uD83C\uDDFB",
"continent": "Europe"
},
{
"country": "Lebanon",
"flag": "\uD83C\uDDF1\uD83C\uDDE7",
"continent": "Asia"
},
{
"country": "Lesotho",
"flag": "\uD83C\uDDF1\uD83C\uDDF8",
"continent": "Africa"
},
{
"country": "Liberia",
"flag": "\uD83C\uDDF1\uD83C\uDDF7",
"continent": "Africa"
},
{
"country": "Libya",
"flag": "\uD83C\uDDF1\uD83C\uDDFE",
"continent": "Africa"
},
{
"country": "Liechtenstein",
"flag": "\uD83C\uDDF1\uD83C\uDDEE",
"continent": "Europe"
},
{
"country": "Lithuania",
"flag": "\uD83C\uDDF1\uD83C\uDDF9",
"continent": "Europe"
},
{
"country": "Luxembourg",
"flag": "\uD83C\uDDF1\uD83C\uDDFA",
"continent": "Europe"
},
{
"country": "Madagascar",
"flag": "\uD83C\uDDF2\uD83C\uDDEC",
"continent": "Africa"
},
{
"country": "Malawi",
"flag": "\uD83C\uDDF2\uD83C\uDDFC",
"continent": "Africa"
},
{
"country": "Malaysia",
"flag": "\uD83C\uDDF2\uD83C\uDDFE",
"continent": "Asia"
},
{
"country": "Maldives",
"flag": "\uD83C\uDDF2\uD83C\uDDFB",
"continent": "Asia"
},
{
"country": "Mali",
"flag": "\uD83C\uDDF2\uD83C\uDDF1",
"continent": "Africa"
},
{
"country": "Malta",
"flag": "\uD83C\uDDF2\uD83C\uDDF9",
"continent": "Europe"
},
{
"country": "Marshall Islands",
"flag": "\uD83C\uDDF2\uD83C\uDDED",
"continent": "Oceania"
},
{
"country": "Mauritania",
"flag": "\uD83C\uDDF2\uD83C\uDDF7",
"continent": "Africa"
},
{
"country": "Mauritius",
"flag": "\uD83C\uDDF2\uD83C\uDDFA",
"continent": "Africa"
},
{
"country": "Mexico",
"flag": "\uD83C\uDDF2\uD83C\uDDFD",
"continent": "North America"
},
{
"country": "Micronesia",
"flag": "\uD83C\uDDEB\uD83C\uDDF2",
"continent": "Oceania"
},
{
"country": "Moldova",
"flag": "\uD83C\uDDF2\uD83C\uDDE9",
"continent": "Europe"
},
{
"country": "Monaco",
"flag": "\uD83C\uDDF2\uD83C\uDDE8",
"continent": "Europe"
},
{
"country": "Mongolia",
"flag": "\uD83C\uDDF2\uD83C\uDDF3",
"continent": "Asia"
},
{
"country": "Montenegro",
"flag": "\uD83C\uDDF2\uD83C\uDDEA",
"continent": "Europe"
},
{
"country": "Morocco",
"flag": "\uD83C\uDDF2\uD83C\uDDE6",
"continent": "Africa"
},
{
"country": "Mozambique",
"flag": "\uD83C\uDDF2\uD83C\uDDFF",
"continent": "Africa"
},
{
"country": "Myanmar (Burma)",
"flag": "\uD83C\uDDF2\uD83C\uDDF2",
"continent": "Asia"
},
{
"country": "Namibia",
"flag": "\uD83C\uDDF3\uD83C\uDDE6",
"continent": "Africa"
},
{
"country": "Nauru",
"flag": "\uD83C\uDDF3\uD83C\uDDF7",
"continent": "Oceania"
},
{
"country": "Nepal",
"flag": "\uD83C\uDDF3\uD83C\uDDF5",
"continent": "Asia"
},
{
"country": "Netherlands",
"flag": "\uD83C\uDDF3\uD83C\uDDF1",
"continent": "Europe"
},
{
"country": "New Zealand",
"flag": "\uD83C\uDDF3\uD83C\uDDFF",
"continent": "Oceania"
},
{
"country": "Nicaragua",
"flag": "\uD83C\uDDF3\uD83C\uDDEE",
"continent": "North America"
},
{
"country": "Niger",
"flag": "\uD83C\uDDF3\uD83C\uDDEA",
"continent": "Africa"
},
{
"country": "Nigeria",
"flag": "\uD83C\uDDF3\uD83C\uDDEC",
"continent": "Africa"
},
{
"country": "North Macedonia",
"flag": "\uD83C\uDDF2\uD83C\uDDF0",
"continent": "Europe"
},
{
"country": "Norway",
"flag": "\uD83C\uDDF3\uD83C\uDDF4",
"continent": "Europe"
},
{
"country": "Oman",
"flag": "\uD83C\uDDF4\uD83C\uDDF2",
"continent": "Asia"
},
{
"country": "Pakistan",
"flag": "\uD83C\uDDF5\uD83C\uDDF0",
"continent": "Asia"
},
{
"country": "Palau",
"flag": "\uD83C\uDDF5\uD83C\uDDFC",
"continent": "Oceania"
},
{
"country": "Palestine",
"flag": "\uD83C\uDDF5\uD83C\uDDF8",
"continent": "Asia"
},
{
"country": "Panama",
"flag": "\uD83C\uDDF5\uD83C\uDDE6",
"continent": "North America"
},
{
"country": "Papua New Guinea",
"flag": "\uD83C\uDDF5\uD83C\uDDEC",
"continent": "Oceania"
},
{
"country": "Paraguay",
"flag": "\uD83C\uDDF5\uD83C\uDDFE",
"continent": "South America"
},
{
"country": "Peru",
"flag": "\uD83C\uDDF5\uD83C\uDDEA",
"continent": "South America"
},
{
"country": "Philippines",
"flag": "\uD83C\uDDF5\uD83C\uDDED",
"continent": "Asia"
},
{
"country": "Poland",
"flag": "\uD83C\uDDF5\uD83C\uDDF1",
"continent": "Europe"
},
{
"country": "Portugal",
"flag": "\uD83C\uDDF5\uD83C\uDDF9",
"continent": "Europe"
},
{
"country": "Qatar",
"flag": "\uD83C\uDDF6\uD83C\uDDE6",
"continent": "Asia"
},
{
"country": "Romania",
"flag": "\uD83C\uDDF7\uD83C\uDDF4",
"continent": "Europe"
},
{
"country": "Russia",
"flag": "\uD83C\uDDF7\uD83C\uDDFA",
"continent": "Europe"
},
{
"country": "Rwanda",
"flag": "\uD83C\uDDF7\uD83C\uDDFC",
"continent": "Africa"
},
{
"country": "Saint Kitts and Nevis",
"flag": "\uD83C\uDDF0\uD83C\uDDF3",
"continent": "North America"
},
{
"country": "Saint Lucia",
"flag": "\uD83C\uDDF1\uD83C\uDDE8",
"continent": "North America"
},
{
"country": "Saint Vincent and the Grenadines",
"flag": "\uD83C\uDDFB\uD83C\uDDE8",
"continent": "North America"
},
{
"country": "Samoa",
"flag": "\uD83C\uDDFC\uD83C\uDDF8",
"continent": "Oceania"
},
{
"country": "San Marino",
"flag": "\uD83C\uDDF8\uD83C\uDDF2",
"continent": "Europe"
},
{
"country": "São Tomé and Príncipe",
"flag": "\uD83C\uDDF8\uD83C\uDDF9",
"continent": "Africa"
},
{
"country": "Saudi Arabia",
"flag": "\uD83C\uDDF8\uD83C\uDDE6",
"continent": "Asia"
},
{
"country": "Senegal",
"flag": "\uD83C\uDDF8\uD83C\uDDF3",
"continent": "Africa"
},
{
"country": "Serbia",
"flag": "\uD83C\uDDF7\uD83C\uDDF8",
"continent": "Europe"
},
{
"country": "Seychelles",
"flag": "\uD83C\uDDF8\uD83C\uDDE8",
"continent": "Africa"
},
{
"country": "Sierra Leone",
"flag": "\uD83C\uDDF8\uD83C\uDDF1",
"continent": "Africa"
},
{
"country": "Singapore",
"flag": "\uD83C\uDDF8\uD83C\uDDEC",
"continent": "Asia"
},
{
"country": "Slovakia",
"flag": "\uD83C\uDDF8\uD83C\uDDF0",
"continent": "Europe"
},
{
"country": "Slovenia",
"flag": "\uD83C\uDDF8\uD83C\uDDEE",
"continent": "Europe"
},
{
"country": "Solomon Islands",
"flag": "\uD83C\uDDF8\uD83C\uDDE7",
"continent": "Oceania"
},
{
"country": "Somalia",
"flag": "\uD83C\uDDF8\uD83C\uDDF4",
"continent": "Africa"
},
{
"country": "South Africa",
"flag": "\uD83C\uDDFF\uD83C\uDDE6",
"continent": "Africa"
},
{
"country": "South Korea",
"flag": "\uD83C\uDDF0\uD83C\uDDF7",
"continent": "Asia"
},
{
"country": "South Sudan",
"flag": "\uD83C\uDDF8\uD83C\uDDF8",
"continent": "Africa"
},
{
"country": "Spain",
"flag": "\uD83C\uDDEA\uD83C\uDDF8",
"continent": "Europe"
},
{
"country": "Sri Lanka",
"flag": "\uD83C\uDDF1\uD83C\uDDF0",
"continent": "Asia"
},
{
"country": "Sudan",
"flag": "\uD83C\uDDF8\uD83C\uDDE9",
"continent": "Africa"
},
{
"country": "Suriname",
"flag": "\uD83C\uDDF8\uD83C\uDDF7",
"continent": "South America"
},
{
"country": "Sweden",
"flag": "\uD83C\uDDF8\uD83C\uDDEA",
"continent": "Europe"
},
{
"country": "Switzerland",
"flag": "\uD83C\uDDE8\uD83C\uDDED",
"continent": "Europe"
},
{
"country": "Syria",
"flag": "\uD83C\uDDF8\uD83C\uDDFE",
"continent": "Asia"
},
{
"country": "Taiwan",
"flag": "\uD83C\uDDF9\uD83C\uDDFC",
"continent": "Asia"
},
{
"country": "Tajikistan",
"flag": "\uD83C\uDDF9\uD83C\uDDEF",
"continent": "Asia"
},
{
"country": "Tanzania",
"flag": "\uD83C\uDDF9\uD83C\uDDFF",
"continent": "Africa"
},
{
"country": "Thailand",
"flag": "\uD83C\uDDF9\uD83C\uDDED",
"continent": "Asia"
},
{
"country": "Timor-Leste",
"flag": "\uD83C\uDDF9\uD83C\uDDF1",
"continent": "Asia"
},
{
"country": "Togo",
"flag": "\uD83C\uDDF9\uD83C\uDDEC",
"continent": "Africa"
},
{
"country": "Tonga",
"flag": "\uD83C\uDDF9\uD83C\uDDF4",
"continent": "Oceania"
},
{
"country": "Trinidad and Tobago",
"flag": "\uD83C\uDDF9\uD83C\uDDF9",
"continent": "North America"
},
{
"country": "Tunisia",
"flag": "\uD83C\uDDF9\uD83C\uDDF3",
"continent": "Africa"
},
{
"country": "Turkey",
"flag": "\uD83C\uDDF9\uD83C\uDDF7",
"continent": "Asia"
},
{
"country": "Turkmenistan",
"flag": "\uD83C\uDDF9\uD83C\uDDF2",
"continent": "Asia"
},
{
"country": "Tuvalu",
"flag": "\uD83C\uDDF9\uD83C\uDDFB",
"continent": "Oceania"
},
{
"country": "Uganda",
"flag": "\uD83C\uDDFA\uD83C\uDDEC",
"continent": "Africa"
},
{
"country": "Ukraine",
"flag": "\uD83C\uDDFA\uD83C\uDDE6",
"continent": "Europe"
},
{
"country": "United Arab Emirates",
"flag": "\uD83C\uDDE6\uD83C\uDDEA",
"continent": "Asia"
},
{
"country": "United Kingdom",
"flag": "\uD83C\uDDEC\uD83C\uDDE7",
"continent": "Europe"
},
{
"country": "United States",
"flag": "\uD83C\uDDFA\uD83C\uDDF8",
"continent": "North America"
},
{
"country": "Uruguay",
"flag": "\uD83C\uDDFA\uD83C\uDDFE",
"continent": "South America"
},
{
"country": "Uzbekistan",
"flag": "\uD83C\uDDFA\uD83C\uDDFF",
"continent": "Asia"
},
{
"country": "Vanuatu",
"flag": "\uD83C\uDDFB\uD83C\uDDFA",
"continent": "Oceania"
},
{
"country": "Vatican City",
"flag": "\uD83C\uDDFB\uD83C\uDDE6",
"continent": "Europe"
},
{
"country": "Venezuela",
"flag": "\uD83C\uDDFB\uD83C\uDDEA",
"continent": "South America"
},
{
"country": "Vietnam",
"flag": "\uD83C\uDDFB\uD83C\uDDF3",
"continent": "Asia"
},
{
"country": "Yemen",
"flag": "\uD83C\uDDFE\uD83C\uDDEA",
"continent": "Asia"
},
{
"country": "Zambia",
"flag": "\uD83C\uDDFF\uD83C\uDDF2",
"continent": "Africa"
},
{
"country": "Zimbabwe",
"flag": "\uD83C\uDDFF\uD83C\uDDFC",
"continent": "Africa"
}
]
